chromecap/__init__.py
chromecap/server/__init__.py
chromecap/server/cli.py
chromecap-0.2.0.dist-info/licenses/LICENSE
client/__init__.py
client/index.html
client/static/README.md
client/static/__init__.py
client/static/client.js
client/static/debug-tools.js
client/static/styles.css
extension/README-BGPT-Integration.md
extension/__init__.py
extension/debug-helper.js
extension/manifest.json
extension/src/background.js
extension/src/content.js
server/__init__.py
server/cli.py
server/app/__init__.py
server/app/config.py
server/app/main.py
chromecap-0.2.0.dist-info/METADATA
chromecap-0.2.0.dist-info/WHEEL
chromecap-0.2.0.dist-info/entry_points.txt
chromecap-0.2.0.dist-info/top_level.txt
chromecap-0.2.0.dist-info/RECORD
