Metadata-Version: 2.4
Name: chromecap
Version: 0.2.0
Summary: Screenshot capture, console log extraction, interactive page actions, and AI-powered visual analysis for UI testing & debugging via terminal
Home-page: https://github.com/civai-technologies/chrome-cap
Author: Nifemi Alpine
Author-email: hello@civai.co
Classifier: Development Status :: 4 - Beta
Classifier: Intended Audience :: Developers
Classifier: License :: OSI Approved :: MIT License
Classifier: Programming Language :: Python :: 3
Classifier: Programming Language :: Python :: 3.9
Classifier: Programming Language :: Python :: 3.10
Classifier: Programming Language :: Python :: 3.11
Classifier: Topic :: Software Development :: Libraries :: Python Modules
Classifier: Topic :: Utilities
Requires-Python: >=3.9
License-File: LICENSE
Requires-Dist: click>=8.0.0
Requires-Dist: fastapi>=0.95.0
Requires-Dist: uvicorn>=0.15.0
Requires-Dist: requests>=2.25.0
Requires-Dist: python-socketio>=5.1.0
Requires-Dist: python-engineio>=4.0.0
Requires-Dist: tabulate>=0.8.9
Requires-Dist: python-dotenv>=0.19.0
Requires-Dist: psutil>=5.8.0
Requires-Dist: pydantic>=1.10.0
Requires-Dist: cursor-agent-tools>=0.1.29
Requires-Dist: beautifulsoup4>=4.12.0
Provides-Extra: dev
Requires-Dist: pytest>=7.0.0; extra == "dev"
Requires-Dist: pytest-cov>=4.0.0; extra == "dev"
Requires-Dist: black>=23.0.0; extra == "dev"
Requires-Dist: flake8>=6.0.0; extra == "dev"
Requires-Dist: mypy>=1.0.0; extra == "dev"
Requires-Dist: isort>=5.10.0; extra == "dev"
Requires-Dist: pre-commit>=3.0.0; extra == "dev"
Dynamic: author
Dynamic: author-email
Dynamic: classifier
Dynamic: description
Dynamic: description-content-type
Dynamic: home-page
Dynamic: license-file
Dynamic: provides-extra
Dynamic: requires-dist
Dynamic: requires-python
Dynamic: summary
